{
  "activities": [],
  "description": "Your training with weapons allows you to use the mastery properties of two kinds of weapons of your choice with which you have proficiency, such as Daggers and Shortbows.\n\nWhenever you finish a Long Rest, you can change the kinds of weapons you chose. For example, you could switch to using the mastery properties of Scimitars and Shortswords.",
  "entry_kind": "feature",
  "feature_type": "class_feature",
  "foundry_id": "phbrgeWeaponMast",
  "name": "Weapon Mastery",
  "passive_effects": [],
  "provenance": {
    "ingest_date": "2026-05-30",
    "ingest_version": "foundry-translator-v1",
    "license_tag": "CC-BY-4.0",
    "source": "foundry",
    "source_url": "https://github.com/foundryvtt/dnd5e/blob/965ad2d0cf5d063dac675ba078b5bd3c3c0dd449/packs/_source/classes24/rogue/class-features/weapon-mastery.yml",
    "srd_version": [
      "5.2"
    ]
  },
  "review": {
    "known_divergence": null,
    "requires_user_decision": false
  },
  "slug": "weapon-mastery",
  "source_slug": "rogue"
}